aidkit_client/__init__.py
aidkit_client/_download_manager/README.md
aidkit_client/_download_manager/__init__.py
aidkit_client/_download_manager/async_download_manager.py
aidkit_client/_download_manager/caching_file_getter_proxy.py
aidkit_client/_download_manager/download_facade.py
aidkit_client/_download_manager/download_images_to_memory.py
aidkit_client/_download_manager/download_storage.py
aidkit_client/_download_manager/downloaded_files_progress_tracker.py
aidkit_client/_download_manager/http_download.py
aidkit_client/_download_manager/interfaces/__init__.py
aidkit_client/_download_manager/interfaces/data_structures.py
aidkit_client/_download_manager/interfaces/download_manager_interface.py
aidkit_client/_download_manager/interfaces/get_file_interface.py
aidkit_client/_download_manager/interfaces/get_local_path_interface.py
aidkit_client/_download_manager/interfaces/key_value_storage_interface.py
aidkit_client/_download_manager/interfaces/progress_tracking_interfaces.py
aidkit_client/_download_manager/interfaces/subscribable_interface.py
aidkit_client/_download_manager/key_hashing_for_key_value_storage_proxy.py
aidkit_client/_download_manager/local_path_for_storage_path_getter_proxy.py
aidkit_client/_download_manager/progress_tracking_download_manager_proxy.py
aidkit_client/_download_manager/progress_tracking_file_getter_proxy.py
aidkit_client/_download_manager/resize_images_download_storage_proxy.py
aidkit_client/_download_manager/retrying_file_getter_proxy.py
aidkit_client/_download_manager/same_local_path_as_remote_path_getter.py
aidkit_client/_download_manager/utils.py
aidkit_client/_endpoints/__init__.py
aidkit_client/_endpoints/augmentations.py
aidkit_client/_endpoints/constants.py
aidkit_client/_endpoints/datasets.py
aidkit_client/_endpoints/depth_maps.py
aidkit_client/_endpoints/ml_models.py
aidkit_client/_endpoints/models.py
aidkit_client/_endpoints/observations.py
aidkit_client/_endpoints/pagination.py
aidkit_client/_endpoints/pipeline_runs.py
aidkit_client-0.11.0.dist-info/LICENSE
aidkit_client-0.11.0.dist-info/METADATA
aidkit_client-0.11.0.dist-info/WHEEL
aidkit_client-0.11.0.dist-info/RECORD
